{
    "module": "linear-gradient",
    "template": "module-class",
    "differences": [
        {
            "code": "type-empty-intersection",
            "parameterExpected": {
                "name": "colors",
                "type": {
                    "kind": "tuple_type",
                    "value": [
                        {
                            "kind": "primitive_keyword",
                            "value": "number"
                        },
                        {
                            "kind": "primitive_keyword",
                            "value": "number"
                        },
                        {
                            "kind": "primitive_keyword",
                            "value": "number"
                        }
                    ]
                },
                "optional": false,
                "modifiers": [],
                "dotDotDotToken": false
            },
            "parameterActual": {
                "name": "colors",
                "type": {
                    "kind": "array_type",
                    "value": {
                        "kind": "primitive_keyword",
                        "value": "number"
                    }
                },
                "optional": false,
                "modifiers": [],
                "dotDotDotToken": false
            }
        }
    ],
    "tags": [
        "type-array",
        "number",
        "type-tuple",
        "alias-type",
        "string"
    ]
}
