{
    "module": "luaparse",
    "template": "module",
    "differences": [
        {
            "code": "function-extra",
            "functionActual": {
                "name": "end",
                "returnType": {
                    "kind": "object_keyword",
                    "value": "object"
                },
                "parameters": [
                    {
                        "name": "_input",
                        "type": {
                            "kind": "undefined_keyword",
                            "value": "undefined"
                        },
                        "optional": true,
                        "modifiers": [],
                        "dotDotDotToken": false
                    }
                ],
                "modifiers": [
                    "export"
                ],
                "typeParameters": [],
                "_isConstructor": false
            }
        },
        {
            "code": "function-extra",
            "functionActual": {
                "name": "lex",
                "returnType": {
                    "kind": "object_keyword",
                    "value": "object"
                },
                "parameters": [],
                "modifiers": [
                    "export"
                ],
                "typeParameters": [],
                "_isConstructor": false
            }
        },
        {
            "code": "function-overloading-difference",
            "functionIdentifier": "parse",
            "expectedNumberOfOverloadings": 3,
            "actualNumberOfOverloadings": 1
        },
        {
            "code": "type-empty-intersection",
            "parameterExpected": {
                "name": "options",
                "type": {
                    "kind": "intersection_type",
                    "value": [
                        {
                            "kind": "type_reference",
                            "value": "Partial<Options>",
                            "text": ""
                        },
                        {
                            "kind": "type_interface",
                            "value": {
                                "name": "",
                                "properties": [
                                    {
                                        "name": "wait",
                                        "type": {
                                            "kind": "literal_type",
                                            "value": "true"
                                        },
                                        "optional": false,
                                        "modifiers": [],
                                        "dotDotDotToken": false
                                    }
                                ],
                                "methods": [],
                                "classes": [],
                                "callSignatures": [],
                                "indexSignatures": [],
                                "typeParameters": []
                            }
                        }
                    ]
                },
                "optional": false,
                "modifiers": [],
                "dotDotDotToken": false
            },
            "parameterActual": {
                "name": "_options",
                "type": {
                    "kind": "undefined_keyword",
                    "value": "undefined"
                },
                "optional": true,
                "modifiers": [],
                "dotDotDotToken": false
            }
        },
        {
            "code": "type-non-empty-intersection",
            "parameterExpected": {
                "name": "options",
                "type": {
                    "kind": "type_reference",
                    "value": "Partial<Options>",
                    "text": ""
                },
                "optional": true,
                "modifiers": [],
                "dotDotDotToken": false
            },
            "parameterActual": {
                "name": "_options",
                "circular": true
            }
        },
        {
            "code": "type-empty-intersection",
            "parameterExpected": {
                "name": "options",
                "type": {
                    "kind": "type_reference",
                    "value": "Partial<Options>",
                    "text": ""
                },
                "optional": true,
                "modifiers": [],
                "dotDotDotToken": false
            },
            "parameterActual": {
                "name": "_input",
                "type": {
                    "kind": "primitive_keyword",
                    "value": "string"
                },
                "optional": false,
                "modifiers": [],
                "dotDotDotToken": false
            }
        },
        {
            "code": "extra-parameter",
            "parameterExtra": {
                "name": "_options",
                "circular": true
            }
        }
    ],
    "tags": [
        "boolean",
        "type-function",
        "void",
        "literals",
        "type-union",
        "number",
        "string",
        "type-tuple",
        "type-intersection",
        "optional-parameter"
    ]
}
