{
    "module": "phone-formatter",
    "template": "module",
    "differences": [
        {
            "code": "function-extra",
            "functionActual": {
                "name": "normalize",
                "returnType": {
                    "kind": "primitive_keyword",
                    "value": "string"
                },
                "parameters": [
                    {
                        "name": "phoneNumber",
                        "type": {
                            "kind": "primitive_keyword",
                            "value": "string"
                        },
                        "optional": false,
                        "modifiers": [],
                        "dotDotDotToken": false
                    }
                ],
                "modifiers": [
                    "export"
                ],
                "typeParameters": [],
                "_isConstructor": false
            }
        }
    ],
    "tags": [
        "optional-parameter"
    ]
}
