{"9":[1,15,1,22],"10":[4,3,5,15],"17":[1,23,1,40],"18":[4,3,6,15],"25":[1,15,1,41],"26":[4,3,7,12],"33":[1,15,1,41],"41":[1,15,1,41],"49":[4,3,4,15],"57":[5,3,5,15],"65":[6,3,6,15],"73":[7,3,7,12],"81":[4,3,7,12],"89":[4,3,7,12],"97":[9,19,9,26],"105":[9,27,9,39],"113":[9,15,9,40],"121":[9,15,9,40],"129":[9,15,9,40],"137":[11,14,11,21],"145":[11,14,11,29],"147":[11,14,11,27],"153":[11,14,11,29],"161":[11,14,11,29],"169":[1,1,12,1],"177":[1,1,12,1],"185":[1,1,12,1],"193":[1,1,12,1],"201":[1,1,12,1],"209":[1,1,12,1],"217":[1,1,12,1],"nBranches":0,"originalCodeFileName":"/tmp/runtimeAnalysis/index.js","instrumentedCodeFileName":"/tmp/runtimeAnalysis/index_jalangi_.js","code":"var OBJFile = require('obj-file-parser');\n\nvar fileContents =\n  'v 0 0 0 \\n' +\n  'v 0 1 0 \\n' +\n  'v 1 0 0 \\n' +\n  'f 1 2 3';\n\nvar objFile = new OBJFile(fileContents);\n\nvar output = objFile.parse(); // see description below\n"}